{
  "parent": "minecraft:recipes/root",
  "criteria": {
    "has_shard": {
      "conditions": {
        "items": [
          {
            "tag": "chakral:shards"
          }
        ]
      },
      "trigger": "minecraft:inventory_changed"
    },
    "has_the_recipe": {
      "conditions": {
        "recipe": "chakral:shard_refiner"
      },
      "trigger": "minecraft:recipe_unlocked"
    }
  },
  "requirements": [
    [
      "has_shard",
      "has_the_recipe"
    ]
  ],
  "rewards": {
    "recipes": [
      "chakral:shard_refiner"
    ]
  }
}